stocks/__init__.py
stocks/mymodule.py
stocksymboltools-0.2.dist-info/LICENSE.txt
stocksymboltools-0.2.dist-info/METADATA
stocksymboltools-0.2.dist-info/WHEEL
stocksymboltools-0.2.dist-info/top_level.txt
stocksymboltools-0.2.dist-info/RECORD
