Metadata-Version: 2.1
Name: stocksymboltools
Version: 0.2
Summary: A library to get stock symbols
Home-page: https://github.com/pavan-krishna123/stocks
Author: Pavan krishna
Author-email: narne.pavankrishna1@gmail.com
Classifier: License :: OSI Approved :: MIT License
Classifier: Programming Language :: Python
Classifier: Programming Language :: Python :: 3
Classifier: Programming Language :: Python :: 3.7
License-File: LICENSE.txt
Requires-Dist: pandas
